devtools/GUIdemo.py
devtools/__init__.py
project/AES256util.py
project/__init__.py
project/add.py
project/config.py
project/dbconfig.py
project/modify.py
project/pm.py
project/retrieve.py
project/tkinter_bootstrap_sample.py
protect_unibo-0.1.0.dist-info/licenses/LICENSE.md
tests/__init__.py
tests/test_config.py
tests/test_dbconfig.py
ui/__init__.py
ui/CONTROLLER/GUIcontroller.py
ui/CONTROLLER/Logincontroller.py
ui/CONTROLLER/__init__.py
ui/MODEL/GUImodel.py
ui/MODEL/__init__.py
ui/VIEW/GUIview.py
ui/VIEW/Loginview.py
ui/VIEW/__init__.py
protect_unibo-0.1.0.dist-info/METADATA
protect_unibo-0.1.0.dist-info/WHEEL
protect_unibo-0.1.0.dist-info/top_level.txt
protect_unibo-0.1.0.dist-info/RECORD
